numify/__init__.py
numify/numify.py
numify/numify_test.py
numify-1.0.1.dist-info/LICENSE
numify-1.0.1.dist-info/METADATA
numify-1.0.1.dist-info/WHEEL
numify-1.0.1.dist-info/top_level.txt
numify-1.0.1.dist-info/RECORD
