Metadata-Version: 2.1
Name: numify
Version: 1.0.1
Summary: Convert alphanumeric characters to integers i.e 1k to 1000
Home-page: https://github.com/boadley/numify
Author: jaboadley
Author-email: numify@mailinator.com
License: MIT
Platform: UNKNOWN
Classifier: License :: OSI Approved :: MIT License
Classifier: Programming Language :: Python :: 3
Classifier: Programming Language :: Python :: 3.7
